frameperfect.py
frameperfect-0.1.0a1.dist-info/licenses/LICENSE
frameperfect-0.1.0a1.dist-info/METADATA
frameperfect-0.1.0a1.dist-info/WHEEL
frameperfect-0.1.0a1.dist-info/top_level.txt
frameperfect-0.1.0a1.dist-info/RECORD
