Metadata-Version: 2.4
Name: frameperfect
Version: 0.1.0a1
Summary: A lightweight GUI application for precise frame-by-frame video analysis and screenshot extraction, built with PySide/PyQt and OpenCV.
Author-email: Jifeng Wu <jifengwu2k@gmail.com>
License-Expression: AGPL-3.0
Project-URL: Homepage, https://github.com/jifengwu2k/frameperfect
Project-URL: Bug Tracker, https://github.com/jifengwu2k/frameperfect/issues
Classifier: Programming Language :: Python :: 2
Classifier: Programming Language :: Python :: 3
Classifier: Operating System :: OS Independent
Requires-Python: >=2
License-File: LICENSE
Requires-Dist: attrs
Requires-Dist: detect-qt-binding
Requires-Dist: numpy
Requires-Dist: opencv-python-headless
Dynamic: license-file
